exa_py/__init__.py
exa_py/api.py
exa_py/utils.py
exa_py_beta-1.0.16b2.dist-info/METADATA
exa_py_beta-1.0.16b2.dist-info/WHEEL
exa_py_beta-1.0.16b2.dist-info/top_level.txt
exa_py_beta-1.0.16b2.dist-info/RECORD
