Metadata-Version: 2.1
Name: exa-py-beta
Version: 1.0.16b2
Summary: [Beta] Python SDK for Exa API.
Home-page: https://github.com/exa-labs/exa-py-beta
Author: Exa
Author-email: hello@exa.ai
License: UNKNOWN
Platform: UNKNOWN
Classifier: Development Status :: 5 - Production/Stable
Classifier: Intended Audience :: Developers
Classifier: License :: OSI Approved :: MIT License
Classifier: Typing :: Typed
Classifier: Programming Language :: Python :: 3.7
Classifier: Programming Language :: Python :: 3.8
Classifier: Programming Language :: Python :: 3.9
Classifier: Programming Language :: Python :: 3.10
Classifier: Programming Language :: Python :: 3.11
Classifier: Programming Language :: Python :: 3.12
Requires-Dist: requests
Requires-Dist: typing-extensions
Requires-Dist: openai >=1.10.0
